setup.py
lib/jcp/__init__.py
lib/jcp.egg-info/PKG-INFO
lib/jcp.egg-info/SOURCES.txt
lib/jcp.egg-info/dependency_links.txt
lib/jcp.egg-info/requires.txt
lib/jcp.egg-info/top_level.txt
scripts/jcp