Metadata-Version: 1.0
Name: jcp
Version: 0.1.1
Summary: Template aware copy tool.
Home-page: http://github.com/mpdehaan/jcp/
Author: Michael DeHaan
Author-email: michael.dehaan@gmail.com
License: Apache2
Platform: UNKNOWN
